{
  "map": {
    "grid_size": 30,
    "start_pos": [0, 0],
    "goal_pos": [29, 29]
  },
  "enemies": [
    {
      "id": 1,
      "pos": [4, 5],
      "theta": 225.0,
      "alpha": 110.0,
      "comment": "起点附近包围，需要低风险突破",
      "detection_zones": [
        {"r": 3, "p": 0.9},
        {"r": 6, "p": 0.55},
        {"r": 9, "p": 0.3}
      ]
    },
    {
      "id": 2,
      "pos": [8, 4],
      "theta": 250.0,
      "alpha": 80.0,
      "comment": "补充起点下方覆盖",
      "detection_zones": [
        {"r": 3, "p": 0.85},
        {"r": 5, "p": 0.45},
        {"r": 8, "p": 0.2}
      ]
    }
  ]
}
